aws_ip_ranges/__init__.py
aws_ip_ranges/cli.py
aws_ip_ranges/data.py
aws_ip_ranges/output.py
aws_ip_ranges-1.1.1.dist-info/DESCRIPTION.rst
aws_ip_ranges-1.1.1.dist-info/METADATA
aws_ip_ranges-1.1.1.dist-info/RECORD
aws_ip_ranges-1.1.1.dist-info/WHEEL
aws_ip_ranges-1.1.1.dist-info/entry_points.txt
aws_ip_ranges-1.1.1.dist-info/metadata.json
aws_ip_ranges-1.1.1.dist-info/top_level.txt
