Metadata-Version: 2.0
Name: aws-ip-ranges
Version: 1.1.1
Summary: Retrieves and processes AWS IP ranges data.
Home-page: https://github.com/pmuller/aws-ip-ranges
Author: Philippe Muller
Author-email: philippe.muller@gmail.com
License: Apache License 2.0
Platform: UNKNOWN
Classifier: Development Status :: 5 - Production/Stable
Classifier: Programming Language :: Python :: 2.7
Classifier: Programming Language :: Python :: 3.4
Classifier: Programming Language :: Python :: 3.5
Classifier: Programming Language :: Python :: 3.6
Classifier: Topic :: System :: Networking
Classifier: Intended Audience :: System Administrators
Requires-Python: >=2.7, !=3.0.*, !=3.1.*, !=3.2.*, !=3.3.*, <4
Requires-Dist: netaddr (>=0.7.19)
Requires-Dist: PyYAML (>=3.12)
Requires-Dist: requests (>=2.18.4)
